cmip_metric/__init__.py
cmip_metric/divergence.py
cmip_metric/knn.py
cmip_metric/metric.py
cmip_metric/util.py
cmip_metric-0.1.2.dist-info/LICENSE
cmip_metric-0.1.2.dist-info/WHEEL
cmip_metric-0.1.2.dist-info/METADATA
cmip_metric-0.1.2.dist-info/RECORD
